<?xml version="1.0" encoding="UTF-8" standalone="yes"?>
<sst xmlns="http://schemas.openxmlformats.org/spreadsheetml/2006/main" count="1455" uniqueCount="405"><si><t>第１条（契約の目的）</t></si><si><t>第２条（契約期間）</t></si><si><t>第３条（専門相談員）</t></si><si><t>第４条（（介護予防）福祉用具貸与の内容）</t></si><si><t>第５条（福祉用具貸与計画の作成）</t></si><si><t>第６条（サービス提供の記録）</t></si><si><t>第７条（料金）</t></si><si><t>種目</t></si><si><t>月額料金</t></si><si><t>数量</t></si><si><t>利用者負担</t></si><si><t>初月利用者負担</t></si><si><t>特殊寝台</t></si><si><t>特殊寝台付属品</t></si><si><t>合　計</t></si><si><t>第８条（（介護予防）福祉用具貸与の変更）</t></si><si><t>　３　前記第２項については、同一製品に限り有効で、他製品への変更は、遠慮させていただきます。</t></si><si><t>第９条（料金の変更）</t></si><si><t>第１０条（契約の終了）</t></si><si><t>　３　次の事由に該当した場合は､利用者は文書で通知することにより､直ちにこの契約を解約することができます｡</t></si><si><t>　４　次の事由に該当した場合は､事業者は文書で通知することにより､直ちにこの契約を解約することができます｡</t></si><si><t>　５　次の事由に該当した場合は､この契約は自動的に終了します｡</t></si><si><t>第１１条（守秘義務）</t></si><si><t>第１２条（利用者及びその家族等の義務）</t></si><si><t>第１３条（福祉用具の保管･消毒）</t></si><si><t>第１４条（賠償責任）</t></si><si><t>【個人情報の取り扱いについて】</t></si><si><t>　　</t></si><si><t>利用者　　</t></si><si><r><t>＜住　所＞</t></r><r><rPr><u/><sz val="10"/><color theme="1"/><rFont val="ＭＳ Ｐゴシック"/><family val="3"/><charset val="128"/></rPr><t>　　　　　　　　　　　　　　　　　　　　　　　　　　　　　　　　　　　　　　　　　　　　　　　</t></r></si><si><r><t>＜氏　名＞</t></r><r><rPr><u/><sz val="10"/><color theme="1"/><rFont val="ＭＳ Ｐゴシック"/><family val="3"/><charset val="128"/></rPr><t>　　　　　　　　　　　　　　　　　　　　　　　　　　　　　　　　　　　　印</t></r></si><si><t>代理人　　</t></si><si><t>事　業　者</t></si><si><t>福祉用具貸与重要事項説明書</t></si><si><t>○管理者　</t></si><si><t>重要事項</t></si><si><t>1．事業所の概要</t></si><si><t>事　業　者　名</t></si><si><t>福 祉 用 具 貸 与 事 業 所 名</t></si><si><t>事　業　所　所　在　地</t></si><si><t>介護保険指定番号及びその他サービス</t></si><si><t>管理者・連絡先</t></si><si><t>通常の事業の実施地域</t></si><si><t>　　※通常のサービス提供地域以外の方も希望される方はご気軽にご相談ください。</t></si><si><t>２．事業所の職員体制　</t></si><si><t>職種</t></si><si><t>常　　　勤</t></si><si><t>非　常　勤</t></si><si><t>管理者 兼 専門相談員</t></si><si><t>１名</t></si><si><t>０名</t></si><si><t>専門相談員</t></si><si><t>事務･配送職員</t></si><si><t>３．営業日・営業時間</t></si><si><t>営業日</t></si><si><t>月曜日～金曜日</t></si><si><t>注）土・日曜、祝祭日、夏期休暇（8／13～8／15）、年末年始休暇（12／30～1／3）を休業とする。</t></si><si><t>車いす</t></si><si><t>車いす付属品</t></si><si><t>褥瘡予防用具</t></si><si><t>体位変換機</t></si><si><t>手すり</t></si><si><t>スロープ</t></si><si><t>歩行器</t></si><si><t>歩行補助杖</t></si><si><t>認知症老人徘徊感知機器</t></si><si><t>移動用リフト</t></si><si><t>自動排泄処理装置</t></si><si><r><t>　　</t></r><r><rPr><sz val="10"/><color theme="1"/><rFont val="ＭＳ Ｐゴシック"/><family val="3"/><charset val="128"/></rPr><t>介護予防福祉用具貸与にて取り扱う福祉用具の種目は、以下のとおりです。</t></r></si><si><t>歩行補助つえ</t></si><si><t>５．サービスの利用方法</t></si><si><t>　（１）サービスの利用開始</t></si><si><t>　 （２）サービスの終了</t></si><si><t>　　　②当社の都合によりサービスを終了する場合（終了1ヶ月前までに通知します。）</t></si><si><t>　　　③自動終了</t></si><si><t>６．当社の（介護予防）福祉用具貸与の運営の方針</t></si><si><t>　（１）運営の方針</t></si><si><t>（２）その他重要事項</t></si><si><t>　　　・　専門相談員の資質向上のために、定期的に福祉用具に関する適切な研修の機会を設けます。</t></si><si><t>７．サービス内容に関する相談･苦情</t></si><si><t>当社以外に、区役所・市役所・町、村役場などでも相談･苦情等に対する窓口があります。</t></si><si><t>千葉市</t></si><si><t>市原市</t></si><si><t>保健福祉部　高齢者支援課</t></si><si><t>０４３６－２３－９８７３</t></si><si><t>木更津市</t></si><si><t>　　　事業者</t></si><si><t>〇　利用者等に福祉用具搬入後、取扱説明書を説明し交付する。</t></si><si><t>〇　利用者等に貸与する福祉用具を使用しながら、使用方法を説明する。</t></si><si><t>〇　当該商品の全国平均貸与価格と、その貸与事業所の貸与価格の両方を利用者に説明する。</t></si><si><r><t>　　　　　　　＜利用者氏名＞　</t></r><r><rPr><u/><sz val="11"/><color theme="1"/><rFont val="ＭＳ ゴシック"/><family val="3"/><charset val="128"/></rPr><t>　　　　　　　　　　　　　　　　　</t></r><r><rPr><sz val="11"/><color theme="1"/><rFont val="ＭＳ ゴシック"/><family val="3"/><charset val="128"/></rPr><t>印</t></r></si><si><t>福祉用具納品時確認事項</t></si><si><t>●福祉用具適合確認</t></si><si><t>NO</t></si><si><t>項 目</t></si><si><t>●衛生状態</t></si><si><t>口座自動振替（引き落とし）のご案内</t></si><si><t>引落し指定口座は民間金融機関　及び、郵便局のどちらでもご利用可能です。</t></si><si><t>お支払いの流れは以下のとおりとなります。</t></si><si><r><t>①</t></r><r><rPr><sz val="7"/><color theme="1"/><rFont val="Times New Roman"/><family val="1"/></rPr><t xml:space="preserve">  </t></r><r><rPr><sz val="12"/><color theme="1"/><rFont val="ＭＳ ゴシック"/><family val="3"/><charset val="128"/></rPr><t>ご利用月末締め分ごとにご請求</t></r></si><si><r><t>②</t></r><r><rPr><sz val="7"/><color theme="1"/><rFont val="Times New Roman"/><family val="1"/></rPr><t xml:space="preserve">  </t></r><r><rPr><sz val="12"/><color theme="1"/><rFont val="ＭＳ ゴシック"/><family val="3"/><charset val="128"/></rPr><t>翌月26日～末日までに引落し事前請求明細書郵送</t></r></si><si><r><t>③</t></r><r><rPr><sz val="7"/><color theme="1"/><rFont val="Times New Roman"/><family val="1"/></rPr><t xml:space="preserve">  </t></r><r><rPr><sz val="12"/><color theme="1"/><rFont val="ＭＳ ゴシック"/><family val="3"/><charset val="128"/></rPr><t>翌々月6日引き落とし（土日祭日の場合は翌営業日）</t></r></si><si><t>例）平成31年1月ご利用分についてのご請求</t></si><si><t>②　2/26前後に引落し事前請求明細書郵送（1月分）</t></si><si><t>　　　　　　　　　　　　　　　　　　　　　　　　　</t></si><si><r><t>※</t></r><r><rPr><sz val="7"/><color theme="1"/><rFont val="Times New Roman"/><family val="1"/></rPr><t xml:space="preserve">  </t></r><r><rPr><b/><u/><sz val="12"/><color theme="1"/><rFont val="ＭＳ ゴシック"/><family val="3"/><charset val="128"/></rPr><t>口座振替依頼書の申込人名記入欄にはご利用者様のお名前をご記入ください。</t></r></si><si><r><t>※</t></r><r><rPr><sz val="7"/><color theme="1"/><rFont val="Times New Roman"/><family val="1"/></rPr><t xml:space="preserve">  </t></r><r><rPr><b/><u/><sz val="12"/><color theme="1"/><rFont val="ＭＳ ゴシック"/><family val="3"/><charset val="128"/></rPr><t>申込人住所欄に記入されたご住所へ利用者名で請求書が送付されます。</t></r></si><si><t>介護（介護予防）福祉用具貸与サービス契約書</t><phoneticPr fontId="39"/></si><si><t>　２　貸与する福祉用具の機能、安全性、衛生状態などを考慮し、十分な点検を行います。</t><phoneticPr fontId="39"/></si><si><t>　　す。</t><phoneticPr fontId="39"/></si><si><t>　３　利用者は、当該利用者に関する第１項のサービス実施記録等の複写物の交付を無料で受けることができます。</t><phoneticPr fontId="39"/></si><si><t>　２　搬出入にかかる費用は、現に福祉用具貸与に要した費用に含まれるものとし、別にいただきません。</t><phoneticPr fontId="39"/></si><si><r><t>　　①</t></r><r><rPr><sz val="7"/><color theme="1"/><rFont val="Times New Roman"/><family val="1"/></rPr><t xml:space="preserve">    </t></r><r><rPr><sz val="10"/><color theme="1"/><rFont val="ＭＳ Ｐゴシック"/><family val="3"/><charset val="128"/></rPr><t>事業者が正当な理由なくサービスを提供しない場合</t></r><phoneticPr fontId="39"/></si><si><r><t>　　②</t></r><r><rPr><sz val="7"/><color theme="1"/><rFont val="Times New Roman"/><family val="1"/></rPr><t xml:space="preserve">    </t></r><r><rPr><sz val="10"/><color theme="1"/><rFont val="ＭＳ Ｐゴシック"/><family val="3"/><charset val="128"/></rPr><t>事業者が守秘義務に反した場合</t></r><phoneticPr fontId="39"/></si><si><r><t>　　③</t></r><r><rPr><sz val="7"/><color theme="1"/><rFont val="Times New Roman"/><family val="1"/></rPr><t xml:space="preserve">    </t></r><r><rPr><sz val="10"/><color theme="1"/><rFont val="ＭＳ Ｐゴシック"/><family val="3"/><charset val="128"/></rPr><t>事業者が利用者やその家族などに対して社会理念を逸脱する行為を行った場合</t></r><phoneticPr fontId="39"/></si><si><r><t>　　④</t></r><r><rPr><sz val="7"/><color theme="1"/><rFont val="Times New Roman"/><family val="1"/></rPr><t xml:space="preserve">    </t></r><r><rPr><sz val="10"/><color theme="1"/><rFont val="ＭＳ Ｐゴシック"/><family val="3"/><charset val="128"/></rPr><t>事業者が破産した場合</t></r><phoneticPr fontId="39"/></si><si><r><t>　　①</t></r><r><rPr><sz val="7"/><color theme="1"/><rFont val="Times New Roman"/><family val="1"/></rPr><t xml:space="preserve">    </t></r><r><rPr><sz val="10"/><color theme="1"/><rFont val="ＭＳ Ｐゴシック"/><family val="3"/><charset val="128"/></rPr><t>利用者が介護保健施設に入所した場合</t></r><phoneticPr fontId="39"/></si><si><r><t>　　③</t></r><r><rPr><sz val="7"/><color theme="1"/><rFont val="Times New Roman"/><family val="1"/></rPr><t xml:space="preserve">    </t></r><r><rPr><sz val="10"/><color theme="1"/><rFont val="ＭＳ Ｐゴシック"/><family val="3"/><charset val="128"/></rPr><t>医療機関への入院</t></r><phoneticPr fontId="39"/></si><si><r><t>　　④</t></r><r><rPr><sz val="7"/><color theme="1"/><rFont val="Times New Roman"/><family val="1"/></rPr><t xml:space="preserve">    </t></r><r><rPr><sz val="10"/><color theme="1"/><rFont val="ＭＳ Ｐゴシック"/><family val="3"/><charset val="128"/></rPr><t>利用者が亡くなられたとき</t></r><phoneticPr fontId="39"/></si><si><t>　　　報を用いません｡</t><phoneticPr fontId="39"/></si><si><t>　３　事業者は、利用者が苦情等を申し立てた場合であっても、これを理由にしていかなる不利益な扱いをしません。</t><phoneticPr fontId="39"/></si><si><r><t>＜住　所＞</t></r><r><rPr><u/><sz val="10"/><color theme="1"/><rFont val="ＭＳ Ｐゴシック"/><family val="3"/><charset val="128"/></rPr><t>　　　　　　　　　　　　　　　　　　　　　　　　　　　　　　　　　　　　　　　　　　　　　　　</t></r><phoneticPr fontId="39"/></si><si><t>　　午前9時00分～午後6時00分</t><phoneticPr fontId="39"/></si><si><t>営業時間</t><phoneticPr fontId="39"/></si><si><t>スロープ</t><phoneticPr fontId="39"/></si><si><t>※住宅改修につきましても介護保険により支給されますので、希望される方はご相談ください。</t><phoneticPr fontId="39"/></si><si><t>4．福祉用具貸与の内容等</t><phoneticPr fontId="39"/></si><si><t>　　福祉用具貸与にて取り扱う福祉用具の種目は、以下のとおりです。　</t><phoneticPr fontId="39"/></si><si><t>　　　①お客様の都合によりサービスを終了する場合</t><phoneticPr fontId="39"/></si><si><t>　　　　　やむを得ない事情により、当社よりサービスの提供を終了させていただく場合があります。</t><phoneticPr fontId="39"/></si><si><t>　　　　　以下の場合は、文書による通知がなくても、自動的にサービスを終了させて頂きます。</t><phoneticPr fontId="39"/></si><si><r><t>　　　・</t></r><r><rPr><sz val="7"/><color theme="1"/><rFont val="Times New Roman"/><family val="1"/></rPr><t xml:space="preserve">  </t></r><r><rPr><sz val="10"/><color theme="1"/><rFont val="ＭＳ Ｐゴシック"/><family val="3"/><charset val="128"/></rPr><t>お客様の要介護認定区分が、更新申請などにより、自立と認定された場合（この場合、条件を変更して再</t></r><phoneticPr fontId="39"/></si><si><r><t>　　　・</t></r><r><rPr><sz val="7"/><color theme="1"/><rFont val="Times New Roman"/><family val="1"/></rPr><t xml:space="preserve">  </t></r><r><rPr><sz val="10"/><color theme="1"/><rFont val="ＭＳ Ｐゴシック"/><family val="3"/><charset val="128"/></rPr><t>お客様が介護保健施設に入所された場合</t></r><phoneticPr fontId="39"/></si><si><r><t>　　　・</t></r><r><rPr><sz val="7"/><color theme="1"/><rFont val="Times New Roman"/><family val="1"/></rPr><t xml:space="preserve">  </t></r><r><rPr><sz val="10"/><color theme="1"/><rFont val="ＭＳ Ｐゴシック"/><family val="3"/><charset val="128"/></rPr><t>医療機関へご入院された場合</t></r><phoneticPr fontId="39"/></si><si><r><t>　　　・</t></r><r><rPr><sz val="7"/><color theme="1"/><rFont val="Times New Roman"/><family val="1"/></rPr><t xml:space="preserve">  </t></r><r><rPr><sz val="10"/><color theme="1"/><rFont val="ＭＳ Ｐゴシック"/><family val="3"/><charset val="128"/></rPr><t>お客様が亡くなられた場合</t></r><phoneticPr fontId="39"/></si><si><r><t>　　　④</t></r><r><rPr><sz val="7"/><color theme="1"/><rFont val="Times New Roman"/><family val="1"/></rPr><t xml:space="preserve">    </t></r><r><rPr><sz val="10"/><color theme="1"/><rFont val="ＭＳ Ｐゴシック"/><family val="3"/><charset val="128"/></rPr><t>その他</t></r><phoneticPr fontId="39"/></si><si><t>　　　　　・　当社が正当な理由なく適切なサービスを提供しない場合、守秘義務に反した場合、お客様やその家族な</t><phoneticPr fontId="39"/></si><si><r><t xml:space="preserve">              ＜代理人氏名＞　</t></r><r><rPr><u/><sz val="11"/><color theme="1"/><rFont val="ＭＳ ゴシック"/><family val="3"/><charset val="128"/></rPr><t>　　　　　　　　　　　　　　　　　</t></r><r><rPr><sz val="11"/><color theme="1"/><rFont val="ＭＳ ゴシック"/><family val="3"/><charset val="128"/></rPr><t>印</t></r><phoneticPr fontId="39"/></si><si><t>福祉用具貸与商品</t><phoneticPr fontId="39"/></si><si><t>ご利用者様、ご家族様のご要望に沿ったものでしょうか？</t><phoneticPr fontId="39"/></si><si><t>ご利用者様の身体状況、介護状況、生活環境に真に適したものでしょうか？</t><phoneticPr fontId="39"/></si><si><t>商品説明に不足な点や分かりにくい点はないでしょうか？</t><phoneticPr fontId="39"/></si><si><t>確認</t><rPh sb="0" eb="2"><t>カクニン</t></rPh><phoneticPr fontId="39"/></si><si><t>印</t><rPh sb="0" eb="1"><t>イン</t></rPh><phoneticPr fontId="39"/></si><si><t>納品時に作動させてみた上で、不具合・動きが悪い箇所はございませんか？</t><rPh sb="0" eb="2"><t>ノウヒン</t></rPh><rPh sb="2" eb="3"><t>ジ</t></rPh><rPh sb="4" eb="6"><t>サドウ</t></rPh><rPh sb="11" eb="12"><t>ウエ</t></rPh><rPh sb="14" eb="17"><t>フグアイ</t></rPh><rPh sb="18" eb="19"><t>ウゴ</t></rPh><rPh sb="21" eb="22"><t>ワル</t></rPh><rPh sb="23" eb="25"><t>カショ</t></rPh><phoneticPr fontId="39"/></si><si><t>フレームのゆがみ、ビスの欠落、その他気付く点はございませんか？</t><rPh sb="12" eb="14"><t>ケツラク</t></rPh><rPh sb="17" eb="18"><t>タ</t></rPh><rPh sb="18" eb="20"><t>キヅ</t></rPh><rPh sb="21" eb="22"><t>テン</t></rPh><phoneticPr fontId="39"/></si><si><t>実際に確認（目で見る・触るなど）してみて汚れ、衛生上の問題はないでしょうか？</t><rPh sb="0" eb="2"><t>ジッサイ</t></rPh><rPh sb="3" eb="5"><t>カクニン</t></rPh><rPh sb="6" eb="7"><t>メ</t></rPh><rPh sb="8" eb="9"><t>ミ</t></rPh><rPh sb="11" eb="12"><t>サワ</t></rPh><rPh sb="20" eb="21"><t>ヨゴ</t></rPh><rPh sb="23" eb="26"><t>エイセイジョウ</t></rPh><rPh sb="27" eb="29"><t>モンダイ</t></rPh><phoneticPr fontId="39"/></si><si><t>気になる傷等はございませんでしょうか？</t><rPh sb="0" eb="1"><t>キ</t></rPh><rPh sb="4" eb="5"><t>キズ</t></rPh><rPh sb="5" eb="6"><t>トウ</t></rPh><phoneticPr fontId="39"/></si><si><t xml:space="preserve"> 私は、（介護予防）福祉用具貸与の提供について利用者またはその家族等に対して、契約書</t><phoneticPr fontId="39"/></si><si><t>及び本書面によって重要事項を説明しました。</t><phoneticPr fontId="39"/></si><si><t xml:space="preserve"> 私は、契約書及び本書面によって事業者から福祉用具貸与事業について重要事項及び上記につ</t><phoneticPr fontId="39"/></si><si><t>いて説明を受けました。</t><phoneticPr fontId="39"/></si><si><t>　その他、ご請求方法にご希望がございましたら、担当までお申しつけください。</t><phoneticPr fontId="39"/></si><si><t>　　日までとします。</t><phoneticPr fontId="39"/></si><si><t>　２　契約満了の１週間前までに、利用者から事業者に対して、文書又は口頭で契約終了の申し出がない場合、契約</t><phoneticPr fontId="39"/></si><si><t>　　は自動更新されるものとします。</t><phoneticPr fontId="39"/></si><si><t>　１　福祉用具が適切に選定され、かつ使用されるよう、専門的知識に基づき、利用者からの相談に応じるとともに、</t><phoneticPr fontId="39"/></si><si><t>　　取り扱い説明書等の文書を示して福祉用具の機能、使用方法、利用料金等に関する情報を提供し、個別の福祉</t><phoneticPr fontId="39"/></si><si><t>　　用具の貸与に係る同意を得ます。</t><phoneticPr fontId="39"/></si><si><t>　３　利用者の心身の状況等に応じて福祉用具の調整を行うとともに、当該福祉用具の使用方法、使用上の留意事</t><phoneticPr fontId="39"/></si><si><t>　　項、故障時の対応等を記載した文書を利用者に交付し、十分な説明を行った上で、必要に応じて利用者に実際に</t><phoneticPr fontId="39"/></si><si><t>　　当該福祉用具を使用してもらいながら使用方法の指導を行います。</t><phoneticPr fontId="39"/></si><si><t>　４　貸与した福祉用具の使用状況の定期的な確認を行い、必要な場合は、使用方法の指導又は修理等を行いま</t><phoneticPr fontId="39"/></si><si><t>　　具計画・目標、当該目標を達成する為の具体的なサービスの内容を記載した福祉用具サービス計画を作成致しま</t><phoneticPr fontId="39"/></si><si><t>　　スの実施マニュアル等、サービスの質を利用者が評価するための情報については、いつでも閲覧できます。</t><phoneticPr fontId="39"/></si><si><t>　５　事業者は、利用者から料金の支払いを受けたときは、利用者に対し領収書を発行します。介護保険適用の場合、</t><phoneticPr fontId="39"/></si><si><t>　２　福祉用具サービス計画は、既に居宅サービス計画が作成されている場合はその計画内容に沿って作成致しま</t><phoneticPr fontId="39"/></si><si><t>　３　福祉用具専門相談員は、福祉用具サービス計画の作成にあたり、その内容について利用者又はその家族に対</t><phoneticPr fontId="39"/></si><si><t>　　して説明し、利用者様の同意を得てから計画をすすめてまいります。</t><phoneticPr fontId="39"/></si><si><t>　４　福祉用具専門相談員は、福祉用具サービス計画を作成した際には、当該福祉用具サービス計画を利用者様に</t><phoneticPr fontId="39"/></si><si><t>　　交付致します。</t><phoneticPr fontId="39"/></si><si><t>　　（３）尚、契約起算日が月の１５日以前の場合においては月額の全額を、１６日以降の場合においては１/２の料金</t><phoneticPr fontId="39"/></si><si><t>　２　貸与された福祉用具について、万一不良品などで使い勝手が悪く、他に変更したい場合は、すぐにお申し出くだ</t><phoneticPr fontId="39"/></si><si><t>　　されば、無料で変更します。</t><phoneticPr fontId="39"/></si><si><r><t>　　②</t></r><r><rPr><sz val="7"/><color theme="1"/><rFont val="Times New Roman"/><family val="1"/></rPr><t xml:space="preserve">    </t></r><r><rPr><sz val="10"/><color theme="1"/><rFont val="ＭＳ Ｐゴシック"/><family val="3"/><charset val="128"/></rPr><t>利用者の要介護（要支援）認定区分が、非該当（自立）と認定されたとき（この場合、内容を変更して再度契約</t></r><phoneticPr fontId="39"/></si><si><t>　　　することができます）</t><phoneticPr fontId="39"/></si><si><t>　　（２）利用者負担金は契約開始月については使用月末締めの翌々月６日にご指定の金融機関の口座から引き落</t><phoneticPr fontId="39"/></si><si><t>　　　　　としをさせていただきます。（注）金融機関休業日の場合は翌営業日となります。</t><phoneticPr fontId="39"/></si><si><t>　１　利用者は、身体状況の急変等によって必要とする福祉用具に変更が生じた場合、事業者に対して当該福祉用</t><phoneticPr fontId="39"/></si><si><t>　　具の変更を求めることができます。ただし、製品によっては料金の変更が生じる場合がありますのでご了承下さい。</t><phoneticPr fontId="39"/></si><si><t>　１　事業者は、利用者に対して１ヵ月前までに文書で通知することにより、料金の変更（増額又は減額）を申し出る</t><phoneticPr fontId="39"/></si><si><t>　　ことができます。</t><phoneticPr fontId="39"/></si><si><t>　２　利用者が料金の変更を承諾する場合、新たな料金表に基づく【契約書別紙】を作成し、お互いに取り交わしま</t><phoneticPr fontId="39"/></si><si><t>　３　利用者は料金の変更を承諾しない場合、事業者に対し、文書で通知することにより、この契約を解除することが</t><phoneticPr fontId="39"/></si><si><t>　　できます。</t><phoneticPr fontId="39"/></si><si><t>　　１　事業者及び事業者の使用する者は､（介護予防）福祉用具貸与を提供する上で知り得た利用者及びその家族</t><phoneticPr fontId="39"/></si><si><t>　　　に関する秘密を正当な理由なく第三者に漏らしません｡この守秘義務は契約終了後についても同様です｡</t><phoneticPr fontId="39"/></si><si><t>　　２　事業者は､利用者からあらかじめ文書で同意を得ない限り、サービス担当者会議等において､利用者の個人情</t><phoneticPr fontId="39"/></si><si><t>　　３　利用者等は、事業者の承諾を得ることなく本契約に基づく権利の全部もしくは一部を第三者に譲渡し又は転貸</t><phoneticPr fontId="39"/></si><si><t>　　　することはできません。</t><phoneticPr fontId="39"/></si><si><r><t>　①</t></r><r><rPr><sz val="7"/><color theme="1"/><rFont val="Times New Roman"/><family val="1"/></rPr><t xml:space="preserve">    </t></r><r><rPr><sz val="10"/><color theme="1"/><rFont val="ＭＳ Ｐゴシック"/><family val="3"/><charset val="128"/></rPr><t>利用者が、その疾患・心身状態及び福祉用具の設置・使用環境等、レンタル商品の選定に必要な事項につい</t></r><phoneticPr fontId="39"/></si><si><t>　　て故意にこれを告げず、又は不実の告知を行ったことに起因して損害が発生した場合。</t><phoneticPr fontId="39"/></si><si><r><t>　②</t></r><r><rPr><sz val="7"/><color theme="1"/><rFont val="Times New Roman"/><family val="1"/></rPr><t xml:space="preserve">    </t></r><r><rPr><sz val="10"/><color theme="1"/><rFont val="ＭＳ Ｐゴシック"/><family val="3"/><charset val="128"/></rPr><t>利用者の急激な体調の変化等、事業者の実施した（介護予防）福祉用具貸与サービスを原因としない事由に</t></r><phoneticPr fontId="39"/></si><si><t>　　起因して損害が発生した場合。</t><phoneticPr fontId="39"/></si><si><r><t>　③</t></r><r><rPr><sz val="7"/><color theme="1"/><rFont val="Times New Roman"/><family val="1"/></rPr><t xml:space="preserve">    </t></r><r><rPr><sz val="10"/><color theme="1"/><rFont val="ＭＳ Ｐゴシック"/><family val="3"/><charset val="128"/></rPr><t>利用者又はその家族が、事業者及びサービス従事者の指示・説明に反して行った行為に起因して損害が発</t></r><phoneticPr fontId="39"/></si><si><t>　　生した場合。</t><phoneticPr fontId="39"/></si><si><t>　事業者は、利用者の故意又は重大な過失によってレンタル商品が消失し、又は回収したレンタル商品について通</t><phoneticPr fontId="39"/></si><si><t>額の支払を請求することができます。</t><phoneticPr fontId="39"/></si><si><t>　サービス従業者は、常に身分証を携帯し、初回納品時及び利用者やその家族から提示を求められたときは、いつ</t><phoneticPr fontId="39"/></si><si><t>でも身分証を提示します。</t><phoneticPr fontId="39"/></si><si><t>　１　事業者は、福祉用具貸与の提供にあたり、介護支援専門員及び保健医療サービス又は福祉サービスを提供</t><phoneticPr fontId="39"/></si><si><t>　　する者との密接な関係に努めます。</t><phoneticPr fontId="39"/></si><si><t>　２　事業者は、本契約の内容が変更された場合又は本契約が終了した場合は、その内容を記した書面の写しを</t><phoneticPr fontId="39"/></si><si><t>　　速やかに介護支援専門員に送付します。なお、第１０条２項及び４項に基づいて解約通知をする際は、事前に介</t><phoneticPr fontId="39"/></si><si><t>　　護支援専門員に連絡します。</t><phoneticPr fontId="39"/></si><si><t>　１　事業者は、利用者からの相談･苦情に対する窓口を設置し、当該福祉用具の故障・修理依頼など、（介護予防）</t><phoneticPr fontId="39"/></si><si><t>　　福祉用具貸与に関する利用者の要望、苦情等に対し、迅速に対応します。</t><phoneticPr fontId="39"/></si><si><t>　２　苦情の内容によっては、再発防止のために関係メーカー及び提携先との連携･調整を行います。また、必要に</t><phoneticPr fontId="39"/></si><si><t>　　応じて「苦情処理改善会議」を開催します。</t><phoneticPr fontId="39"/></si><si><t>　２　本契約に定める事項に疑義が生じた場合及び本契約に定めのない事項については、介護保険法令その他諸法</t><phoneticPr fontId="39"/></si><si><t>　　令の定めるところを尊重し、双方の協議の上定めるものとします。</t><phoneticPr fontId="39"/></si><si><t>　当事業所はご利用者様の身体的状況やご家族の状況をケアプラン上必要な情報に限り、ご利用者様担当ケアマ</t><phoneticPr fontId="39"/></si><si><t>ネージャーに報告致します。当事業所内においてのお客様に関するサービス内容の検討や、向上の為のケース会</t><phoneticPr fontId="39"/></si><si><t>議、ケアマネージャー様等関係従事者様とのサービス担当者会議以外に個人情報を用いない事を厳守いたします。</t><phoneticPr fontId="39"/></si><si><t>　　約を解約することができます｡</t><phoneticPr fontId="39"/></si><si><t>　２　事業者は､やむをえない事情がある場合､利用者に対して､１ヵ月間の予告期間をおいて理由を示した文書で通</t><phoneticPr fontId="39"/></si><si><t>　　知することにより､この契約を解約することができます｡</t><phoneticPr fontId="39"/></si><si><r><t>　　①</t></r><r><rPr><sz val="7"/><color theme="1"/><rFont val="Times New Roman"/><family val="1"/></rPr><t xml:space="preserve">    </t></r><r><rPr><sz val="10"/><color theme="1"/><rFont val="ＭＳ Ｐゴシック"/><family val="3"/><charset val="128"/></rPr><t>利用者のサービス料金の支払いが１ヵ月以上遅延し､料金を支払うよう催促したにもかかわらず､３０日以内</t></r><phoneticPr fontId="39"/></si><si><t>　　　に支払われない場合</t><phoneticPr fontId="39"/></si><si><r><t>　　②</t></r><r><rPr><sz val="7"/><color theme="1"/><rFont val="Times New Roman"/><family val="1"/></rPr><t xml:space="preserve">    </t></r><r><rPr><sz val="10"/><color theme="1"/><rFont val="ＭＳ Ｐゴシック"/><family val="3"/><charset val="128"/></rPr><t>利用者又はその家族などが､事業者やサービス提供者に対して本契約を継続しがたいほどの背信行為を行</t></r><phoneticPr fontId="39"/></si><si><t>　　　った場合</t><phoneticPr fontId="39"/></si><si><t>　　３　事業者は､利用者の家族からあらかじめ文書で同意を得ない限り、サービス担当者会議等において、当該家</t><phoneticPr fontId="39"/></si><si><t>　　　族の個人情報を用いません｡</t><phoneticPr fontId="39"/></si><si><t>　　１　利用者及びその家族等は、レンタル商品について定められた使用方法及び使用上の注意事項を遵守する事</t><phoneticPr fontId="39"/></si><si><t>　　　とします。</t><phoneticPr fontId="39"/></si><si><t>　　２　利用者等は、事業者の承諾を得ることなくレンタル商品の仕様変更、加工・改造等を行うことはできません。</t><phoneticPr fontId="39"/></si><si><t>※上記の（介護予防）福祉用具貸与品以外に、腰掛便座、入浴補助用具、等が介護保険制度により購入でき</t><phoneticPr fontId="39"/></si><si><t>ます。</t><phoneticPr fontId="39"/></si><si><t>　　　　まずは、電話等でご連絡ください。当社の専門相談員がご自宅に訪問させていただきます。重要事項を説明し</t><phoneticPr fontId="39"/></si><si><t>　　　た後、正式に契約を結び、サービスの提供を開始します（居宅介護支援事業者に、居宅サービス計画の作成を</t><phoneticPr fontId="39"/></si><si><t>　　　依頼している場合は、事前に当該介護支援専門員とご相談下さい）。</t><phoneticPr fontId="39"/></si><si><t>　　　　ます。この場合、お客様が居宅介護支援事業者に居宅サービス計画の作成を依頼している場合は、当該事</t><phoneticPr fontId="39"/></si><si><t>　　　　業者にも通知してください。</t><phoneticPr fontId="39"/></si><si><t>　　　　　　度契約することができます）</t><phoneticPr fontId="39"/></si><si><t>　　　　　　どに対して社会通念を逸脱する行為を行った場合などは、文書で解約を通知することによって即座にサービ</t><phoneticPr fontId="39"/></si><si><t>　　　　　　スを終了することができます。</t><phoneticPr fontId="39"/></si><si><t xml:space="preserve">           ・　お客様が、サービス利用料金の支払いを１ヶ月以上遅延し、料金を支払うよう催告したにもかかわらず、</t><phoneticPr fontId="39"/></si><si><t>　　　　　　３０日以内に支払わない場合、またはお客様やご家族などが当社のサービス従業者に対して本契約を</t><phoneticPr fontId="39"/></si><si><t>　　　　　　継続しがたいほどの背信行為を行った場合は、文書で通知することにより、直ちにサービスの提供を終</t><phoneticPr fontId="39"/></si><si><t>　　　　　　了させていただく場合があります。</t><phoneticPr fontId="39"/></si><si><t>　　　・　利用者が、可能な限り居宅において、その有する能力に応じて、自立した日常生活を営めるように、利用者の</t><phoneticPr fontId="39"/></si><si><t>　　　 心身の状況、希望及びその置かれている環境を踏まえた適切な福祉用具選定の援助を行います。</t><phoneticPr fontId="39"/></si><si><t>　　　・　利用者の要介護状態の軽減もしくは悪化防止又は要介護状態となることの予防に資するよう、適切な福祉用</t><phoneticPr fontId="39"/></si><si><t xml:space="preserve">        具貸与の提供を行います。</t><phoneticPr fontId="39"/></si><si><t>　　　・　福祉用具貸与の提供にあたっては、貸与する福祉用具の機能、安全性、衛生状態等に関し、十分な説明を</t><phoneticPr fontId="39"/></si><si><t xml:space="preserve">        行った上で、必要に応じて利用者に実際に福祉用具を使用してもらいながら使用方法の指導を行います。</t><phoneticPr fontId="39"/></si><si><t>　　　・　サービス従業者は、業務上知り得た利用者又はその家族の秘密を保持します。又、従業者であったものに、</t><phoneticPr fontId="39"/></si><si><t>　　　・　利用者の身体状態の多様性、変化等に対応することができるように、できる限り多くの種類の福祉用具を取り</t><phoneticPr fontId="39"/></si><si><t>　　　 扱うように努めます。</t><phoneticPr fontId="39"/></si><si><t>　　当社福祉用具貸与事業に関する相談、要望、苦情等は、担当の専門相談員又はお客様サービス係 までご連絡</t><phoneticPr fontId="39"/></si><si><t>　　下さい。　</t><phoneticPr fontId="39"/></si><si><t>れている環境を踏まえて、居宅介護支援事業者の作成する「居宅サービス計画」に沿って、福祉用具が適切に選定さ</t><phoneticPr fontId="39"/></si><si><t>れ、かつ使用されるよう、専門的知識に基づき、利用者からの相談に応じます。</t><phoneticPr fontId="39"/></si><si><t>　１　利用者は事業者に対して、１週間の予告期間を置いて文書又は口頭で通知することにより､この契約を解約する</t><phoneticPr fontId="39"/></si><si><t>　　ことができます｡但し､利用者の病変、急な入院などやむをえない事情がある場合は､１週間以内の通知でもこの契</t><phoneticPr fontId="39"/></si><si><t>③　3/6（引落し日・土日際日の場合は翌営業日）お申し込み頂いた口座より、請求明細</t><phoneticPr fontId="39"/></si><si><t>　当社請求基準により、利用金額月額600円からの適用となりますが、600円未満ご利用</t><phoneticPr fontId="39"/></si><si><t>金額の方については、基準金額600円に満たすまでご請求を差し上げずに、600円満了月</t><phoneticPr fontId="39"/></si><si><t>最短の引き落とし日に一括請求させていただきますのでご了承ください。尚、途中レン</t><phoneticPr fontId="39"/></si><si><t>タル品の一式解約が生じた場合においては、商品引き上げ時に現金精算とさせていただ</t><phoneticPr fontId="39"/></si><si><t>きます。</t><phoneticPr fontId="39"/></si><si><t>①　1月ご利用分締め日</t><phoneticPr fontId="39"/></si><si><t xml:space="preserve">                 ・1ヶ月分ご利用　1/1～1/31</t><phoneticPr fontId="39"/></si><si><t xml:space="preserve">                 ・半月ご利用1/1～1/15、1/16～1/31のどちらかの締め日とします。</t><phoneticPr fontId="39"/></si><si><t>＜受付時間＞　月曜日から金曜日の午前９時～午後６時</t><phoneticPr fontId="39"/></si><si><t>　事業者は、利用者に対し、介護保険認定利用者に対して介護保険法令の趣旨に従って、利用者が可能な限りその</t><phoneticPr fontId="39"/></si><si><t>居宅において、その有する能力に応じて自立した日常生活を営むことが出来るよう、（介護予防）福祉用具貸与を提</t><rPh sb="51" eb="52"><t>ツツミ</t></rPh><phoneticPr fontId="39"/></si><si><t>供し、利用者は、事業者に対してそのサービスに対する料金を支払います。</t><phoneticPr fontId="39"/></si><si><t>　事業者は、一定の研修を修了した専門相談員を配置し、専門相談員は、利用者の心身の状況、要望及びその置か</t><rPh sb="43" eb="45"><t>ヨウボウ</t></rPh><phoneticPr fontId="39"/></si><si><t>　１　福祉用具専門相談員は、利用者の心身の状況、要望及びその置かれている環境を踏まえ、（介護予防）福祉用</t><rPh sb="24" eb="26"><t>ヨウボウ</t></rPh><phoneticPr fontId="39"/></si><si><t>　１　事業者は、サービス提供記録を作成することとし、この契約の終了後２年間保存します。</t><rPh sb="17" eb="19"><t>サクセイ</t></rPh><phoneticPr fontId="39"/></si><si><t>　２　利用者は、事業所の営業時間内にその事業所にて、当該利用者に関する第１項のサービス提供記録やサービ</t><rPh sb="43" eb="45"><t>テイキョウ</t></rPh><phoneticPr fontId="39"/></si><si><t>　　し、介護保険適用外のサービス利用については、全額が利用者の負担となります</t><phoneticPr fontId="39"/></si><si><t>　福祉用具の保管･消毒については、指定居宅サービス等の事業の人員、設置及び運営に関する基準第２０３条</t><rPh sb="17" eb="19"><t>シテイ</t></rPh><rPh sb="19" eb="21"><t>キョタク</t></rPh><rPh sb="25" eb="26"><t>トウ</t></rPh><rPh sb="27" eb="29"><t>ジギョウ</t></rPh><rPh sb="30" eb="32"><t>ジンイン</t></rPh><rPh sb="33" eb="35"><t>セッチ</t></rPh><rPh sb="35" eb="36"><t>オヨ</t></rPh><rPh sb="37" eb="39"><t>ウンエイ</t></rPh><rPh sb="40" eb="41"><t>カン</t></rPh><rPh sb="43" eb="45"><t>キジュン</t></rPh><phoneticPr fontId="39"/></si><si><t>　事業者は､福祉用具貸与サービスの提供に伴い、賠償責任を負う場合に備えて損害保険に加入し、納品時に家</t><phoneticPr fontId="39"/></si><si><t>具に損傷を与えるなど、事業者の責めに帰すべき事由により利用者の生命・身体・財産に損害を及ぼした場合は､</t><phoneticPr fontId="39"/></si><si><t>利用者に対してその損害を賠償します｡ただし、事業者は自己の責に帰すべからざる事由によって生じた損害につ</t><phoneticPr fontId="39"/></si><si><t>いては賠償責任を負いません。とりわけ、以下の事由に該当する場合には、損害賠償責任を免れます。</t><phoneticPr fontId="39"/></si><si><t>常の使用状態を超える著しい破損・汚損等が認められる場合には、利用者等に対して補修費もしくは弁償費相当</t><rPh sb="10" eb="11"><t>イチジル</t></rPh><phoneticPr fontId="39"/></si><si><t>　１　利用者及び事業者は、信義に従い誠実に本契約を履行するものとする。</t><rPh sb="16" eb="17"><t>シタガ</t></rPh><phoneticPr fontId="39"/></si><si><t>　４　利用者は、事業者が発行した請求書に記載されている口座引き落とし日の前日までに、事前にご記入いただい</t><rPh sb="8" eb="11"><t>ジギョウシャ</t></rPh><phoneticPr fontId="39"/></si><si><t>　　た預金口座振替依頼書の指定金融機関の口座に、請求された金額をご入金ください。</t><rPh sb="20" eb="22"><t>コウザ</t></rPh><rPh sb="33" eb="35"><t>ニュウキン</t></rPh><phoneticPr fontId="39"/></si><si><t>●不具合・操作性確認</t><phoneticPr fontId="39"/></si><si><r><t>　</t></r><r><rPr><b/><u/><sz val="12"/><color theme="1"/><rFont val="ＭＳ ゴシック"/><family val="3"/><charset val="128"/></rPr><t>表札が異なる場合は、ご明記くださいませ。</t></r><phoneticPr fontId="39"/></si><si><t>　　書内容の金額を自動引落しいたします。</t><phoneticPr fontId="39"/></si><si><r><t>④</t></r><r><rPr><sz val="7"/><color theme="1"/><rFont val="Times New Roman"/><family val="1"/></rPr><t> </t></r><r><rPr><sz val="7"/><color theme="1"/><rFont val="ＭＳ ゴシック"/><family val="3"/><charset val="128"/></rPr><t>　</t></r><r><rPr><sz val="7"/><color theme="1"/><rFont val="Times New Roman"/><family val="1"/></rPr><t xml:space="preserve"> </t></r><r><rPr><sz val="12"/><color theme="1"/><rFont val="ＭＳ ゴシック"/><family val="3"/><charset val="128"/></rPr><t>3/26前後の2月分引落し事前請求書郵送時に、3/6引落し分（1月分）の領収書を同封い</t></r><phoneticPr fontId="39"/></si><si><t>　　たします。</t><phoneticPr fontId="39"/></si><si><t>　２　利用者が避難所に避難された場合には、サービス提供の場所が変わることになりますので、道路状況・人員体</t><phoneticPr fontId="39"/></si><si><t>　　制・避難所の環境等を考慮した上で、サービスの提供が可能と事業者が判断した場合にのみサービスを提供す</t><phoneticPr fontId="39"/></si><si><t>　　るものとします。</t><phoneticPr fontId="39"/></si><si><t>第１６条（利用者の損害賠償責任）</t><phoneticPr fontId="39"/></si><si><t>第１７条（身分証携帯義務）</t><phoneticPr fontId="39"/></si><si><t>第１８条（連携）</t><phoneticPr fontId="39"/></si><si><t>第１９条（苦情処理）</t><phoneticPr fontId="39"/></si><si><t>第２０条（信義誠実の原則）</t><phoneticPr fontId="39"/></si><si><t>　　　・　利用者が避難所に避難された場合には、サービス提供の場所が変わることになりますので、道路状況・人員</t><phoneticPr fontId="39"/></si><si><t xml:space="preserve">        体制・避難所の環境等を考慮した上で、サービスの提供が可能と事業者が判断した場合にのみサービスを提</t><phoneticPr fontId="39"/></si><si><t xml:space="preserve">        供するものとします。</t><phoneticPr fontId="39"/></si><si><t>第３項の規定に基づき、株式会社インフォゲート、フランスベッド株式会社、野口株式会社にこの業務を委託し、業務</t><rPh sb="0" eb="1"><t>ダイ</t></rPh><phoneticPr fontId="39"/></si><si><t>委託契約書を取り交わした上で、事業所は委託の契約の内容において、保管及び消毒が適切な方法により行われ</t><phoneticPr fontId="39"/></si><si><t>ていることを担保します。</t><phoneticPr fontId="39"/></si><si><t>株式会社 サービスワン</t><phoneticPr fontId="39"/></si><si><t>千葉ムツミ福祉用具高品</t><rPh sb="0" eb="2"><t>チバ</t></rPh><rPh sb="5" eb="7"><t>フクシ</t></rPh><rPh sb="7" eb="9"><t>ヨウグ</t></rPh><rPh sb="9" eb="11"><t>タカシナ</t></rPh><phoneticPr fontId="39"/></si><si><t>・（予防）福祉用具貸与事業　(千葉市 1270402124号)</t><rPh sb="17" eb="18"><t>シ</t></rPh><phoneticPr fontId="39"/></si><si><t>千葉市 市原市　四街道市　習志野市　木更津市　佐倉市</t><rPh sb="8" eb="12"><t>ヨツカイドウシ</t></rPh><rPh sb="13" eb="17"><t>ナラシノシ</t></rPh><rPh sb="18" eb="22"><t>キサラヅシ</t></rPh><rPh sb="23" eb="26"><t>サクラシ</t></rPh><phoneticPr fontId="39"/></si><si><t>１名</t><phoneticPr fontId="39"/></si><si><t>０名</t><phoneticPr fontId="39"/></si><si><t>３名</t><phoneticPr fontId="39"/></si><si><t>＜担　　　　当＞　　本  社　　　　 　お客様サービス係　　　＜電話＞　0436-60-3235</t><phoneticPr fontId="39"/></si><si><t>介護保険事業課</t><rPh sb="0" eb="2"><t>カイゴ</t></rPh><rPh sb="2" eb="4"><t>ホケン</t></rPh><rPh sb="4" eb="6"><t>ジギョウ</t></rPh><rPh sb="6" eb="7"><t>カ</t></rPh><phoneticPr fontId="39"/></si><si><t>四街道市</t><rPh sb="0" eb="4"><t>ヨツカイドウシ</t></rPh><phoneticPr fontId="39"/></si><si><t>福祉サービス部　高齢者支援課</t><rPh sb="0" eb="2"><t>フクシ</t></rPh><rPh sb="6" eb="7"><t>ブ</t></rPh><rPh sb="8" eb="11"><t>コウレイシャ</t></rPh><rPh sb="11" eb="13"><t>シエン</t></rPh><rPh sb="13" eb="14"><t>カ</t></rPh><phoneticPr fontId="39"/></si><si><t>習志野市</t><rPh sb="0" eb="4"><t>ナラシノシ</t></rPh><phoneticPr fontId="39"/></si><si><t>保健福祉部　高齢者支援課　</t><phoneticPr fontId="39"/></si><si><t>福祉部　高齢者支援課　高齢者支援担当</t><rPh sb="11" eb="14"><t>コウレイシャ</t></rPh><rPh sb="14" eb="16"><t>シエン</t></rPh><rPh sb="16" eb="18"><t>タントウ</t></rPh><phoneticPr fontId="39"/></si><si><t>佐倉市</t><rPh sb="0" eb="3"><t>サクラシ</t></rPh><phoneticPr fontId="39"/></si><si><t>福祉部　高齢者支援課</t><phoneticPr fontId="39"/></si><si><t>０４３－２４５－５０６２</t><phoneticPr fontId="39"/></si><si><t>０４３－４２１－６１２７</t><phoneticPr fontId="39"/></si><si><t>０４７－４５４－７５３３</t><phoneticPr fontId="39"/></si><si><t>０４３８－２３－２６３０</t><phoneticPr fontId="39"/></si><si><t>０４３－４８４－６２４３</t><phoneticPr fontId="39"/></si><si><t>　　　　　　＜事業所名＞株式会社サービスワン　千葉ムツミ福祉用具高品</t><rPh sb="23" eb="25"><t>チバ</t></rPh><rPh sb="28" eb="30"><t>フクシ</t></rPh><rPh sb="30" eb="32"><t>ヨウグ</t></rPh><rPh sb="32" eb="34"><t>タカシナ</t></rPh><phoneticPr fontId="39"/></si><si><t>第１５条（災害等発生時のサービス提供）</t><rPh sb="5" eb="7"><t>サイガイ</t></rPh><rPh sb="7" eb="8"><t>トウ</t></rPh><rPh sb="8" eb="10"><t>ハッセイ</t></rPh><rPh sb="10" eb="11"><t>ジ</t></rPh><rPh sb="16" eb="18"><t>テイキョウ</t></rPh><phoneticPr fontId="39"/></si><si><t>　　　・　災害発生時や感染症流行時などの非常時においては、事業者は従業員の安全を確保した上でサービスを提</t><rPh sb="7" eb="9"><t>ハッセイ</t></rPh><rPh sb="9" eb="10"><t>ジ</t></rPh><rPh sb="11" eb="14"><t>カンセンショウ</t></rPh><rPh sb="14" eb="16"><t>リュウコウ</t></rPh><rPh sb="16" eb="17"><t>ジ</t></rPh><rPh sb="20" eb="22"><t>ヒジョウ</t></rPh><phoneticPr fontId="39"/></si><si><t xml:space="preserve"> 　　　供するため、事前に合意した日時・内容通りのサービスが提供できない可能性があります。</t><phoneticPr fontId="39"/></si><si><t>　１　災害発生時や感染症流行時などの非常時においては、事業者は従業員の安全を確保した上でサービスを提供</t><rPh sb="5" eb="7"><t>ハッセイ</t></rPh><rPh sb="7" eb="8"><t>ジ</t></rPh><rPh sb="9" eb="12"><t>カンセンショウ</t></rPh><rPh sb="12" eb="14"><t>リュウコウ</t></rPh><rPh sb="14" eb="15"><t>ジ</t></rPh><rPh sb="18" eb="20"><t>ヒジョウ</t></rPh><phoneticPr fontId="39"/></si><si><t>　　するため、事前に合意した日時・内容通りのサービスが提供できない可能性があります。</t><phoneticPr fontId="39"/></si><si><t>　　　　　サービスの終了を希望する日の1週間前までに文書で通知することにより、サービスを終了することができ</t><phoneticPr fontId="39"/></si><si><t>（介護予防）福祉用具貸与料金一覧表</t><phoneticPr fontId="39"/></si><si><r><t>　１　利用者は、サービスの対価として、</t></r><r><rPr><sz val="10"/><color rgb="FFFF0000"/><rFont val="ＭＳ Ｐゴシック"/><family val="3"/><charset val="128"/></rPr><t>下記の（介護予防）福祉用具貸与料</t></r><r><rPr><sz val="10"/><color theme="1"/><rFont val="ＭＳ Ｐゴシック"/><family val="3"/><charset val="128"/></rPr><t>金一覧表をもとに、</t></r><r><rPr><sz val="10"/><color rgb="FFFF0000"/><rFont val="ＭＳ Ｐゴシック"/><family val="3"/><charset val="128"/></rPr><t>月額料金の1割・2割・</t></r><rPh sb="19" eb="21"><t>カキ</t></rPh><rPh sb="44" eb="46"><t>ゲツガク</t></rPh><rPh sb="46" eb="48"><t>リョウキン</t></rPh><phoneticPr fontId="39"/></si><si><r><t>　</t></r><r><rPr><sz val="10"/><color rgb="FFFF0000"/><rFont val="ＭＳ Ｐゴシック"/><family val="3"/><charset val="128"/></rPr><t>本契約書</t></r><r><rPr><sz val="10"/><color theme="1"/><rFont val="ＭＳ Ｐゴシック"/><family val="3"/><charset val="128"/></rPr><t>の契約内容を証するため、本書２通を作成し、利用者、事業者が署名押印の上、各自１通保有するもの</t></r><rPh sb="2" eb="4"><t>ケイヤク</t></rPh><phoneticPr fontId="39"/></si><si><t>とします。同様に、介護保険制度にて義務づけられているサービス担当者会議の開催が必要と認められる場合にお</t></si><si><t>いて、利用者様の個人情報を用いることについての説明を受け、同意するものといたします。</t></si><si><r><t>　　（１）介護保険の適用がある場合は、料金表のサービス費の1割・2割・3割のいずれかが利用者負担</t></r><r><rPr><sz val="10"/><color rgb="FFFF0000"/><rFont val="ＭＳ Ｐゴシック"/><family val="3"/><charset val="128"/></rPr><t>額</t></r><r><rPr><sz val="10"/><color theme="1"/><rFont val="ＭＳ Ｐゴシック"/><family val="3"/><charset val="128"/></rPr><t>となります。</t></r><rPh sb="48" eb="49"><t>ガク</t></rPh><phoneticPr fontId="39"/></si><si><r><t>　　利用者の負担</t></r><r><rPr><sz val="10"/><color rgb="FFFF0000"/><rFont val="ＭＳ Ｐゴシック"/><family val="3"/><charset val="128"/></rPr><t>額</t></r><r><rPr><sz val="10"/><color theme="1"/><rFont val="ＭＳ Ｐゴシック"/><family val="3"/><charset val="128"/></rPr><t>は原則として</t></r><r><rPr><sz val="10"/><color rgb="FFFF0000"/><rFont val="ＭＳ Ｐゴシック"/><family val="3"/><charset val="128"/></rPr><t>下記</t></r><r><rPr><sz val="10"/><color theme="1"/><rFont val="ＭＳ Ｐゴシック"/><family val="3"/><charset val="128"/></rPr><t>の（介護予防）福祉用具貸与料金一覧表の1割・2割・3割のいずれかです。ただ</t></r><rPh sb="8" eb="9"><t>ガク</t></rPh><rPh sb="15" eb="17"><t>カキ</t></rPh><phoneticPr fontId="39"/></si><si><r><rPr><sz val="10"/><color rgb="FFFF0000"/><rFont val="ＭＳ Ｐゴシック"/><family val="3"/><charset val="128"/></rPr><t>　　3割いずれかの合計額を利用者の負担として</t></r><r><rPr><sz val="10"/><color theme="1"/><rFont val="ＭＳ Ｐゴシック"/><family val="3"/><charset val="128"/></rPr><t>支払います。</t></r><phoneticPr fontId="39"/></si><si><t>2020.07.27</t><phoneticPr fontId="39"/></si><si><t>　３　事業者は当月の利用内容明細を請求書として、使用月の翌月末日までに利用者に交付します。</t><rPh sb="24" eb="26"><t>シヨウ</t></rPh><rPh sb="26" eb="27"><t>ヅキ</t></rPh><phoneticPr fontId="39"/></si><si><t>　　　　＜事業所名＞　株式会社サービスワン　千葉ムツミ福祉用具高品</t><rPh sb="22" eb="24"><t>チバ</t></rPh><rPh sb="27" eb="29"><t>フクシ</t></rPh><rPh sb="29" eb="31"><t>ヨウグ</t></rPh><rPh sb="31" eb="33"><t>タカシナ</t></rPh><phoneticPr fontId="39"/></si><si><t>　　　　＜住 　　所＞  千葉県千葉市若葉区高品町1591-5　三恭ビル0001号室</t><rPh sb="16" eb="19"><t>チバシ</t></rPh><rPh sb="19" eb="22"><t>ワカバク</t></rPh><rPh sb="22" eb="25"><t>タカシナチョウ</t></rPh><rPh sb="32" eb="33"><t>ミ</t></rPh><rPh sb="33" eb="34"><t>ヤスシ</t></rPh><rPh sb="40" eb="41"><t>ゴウ</t></rPh><rPh sb="41" eb="42"><t>シツ</t></rPh><phoneticPr fontId="39"/></si><si><t>千葉県千葉市若葉区高品町1591-5　三恭ビル0001号室</t><rPh sb="3" eb="6"><t>チバシ</t></rPh><rPh sb="6" eb="9"><t>ワカバク</t></rPh><rPh sb="9" eb="12"><t>タカシナチョウ</t></rPh><rPh sb="19" eb="20"><t>ミ</t></rPh><rPh sb="20" eb="21"><t>ヤスシ</t></rPh><rPh sb="27" eb="28"><t>ゴウ</t></rPh><rPh sb="28" eb="29"><t>シツ</t></rPh><phoneticPr fontId="39"/></si><si><t>　　　　　　＜住　　所＞千葉県千葉市若葉区高品町1591-5　三恭ビル0001号室</t><rPh sb="15" eb="18"><t>チバシ</t></rPh><rPh sb="18" eb="21"><t>ワカバク</t></rPh><rPh sb="21" eb="24"><t>タカシナチョウ</t></rPh><rPh sb="31" eb="32"><t>ミ</t></rPh><rPh sb="32" eb="33"><t>ヤスシ</t></rPh><rPh sb="39" eb="40"><t>ゴウ</t></rPh><rPh sb="40" eb="41"><t>シツ</t></rPh><phoneticPr fontId="39"/></si><si><t xml:space="preserve">       従業員でなくなった後においてもこれらの秘密を保持する旨を、従業者との雇用契約の内容とします。</t><phoneticPr fontId="39"/></si><si><t>　　　　を請求させていただきます。解約の場合も同様に月の１５日以前の解約については月額の１/２を、１６日以降</t><rPh sb="52" eb="54"><t>イコウ</t></rPh><phoneticPr fontId="39"/></si><si><t>　　　　の解約については１ヵ月分の料金を請求させていただきます。</t><phoneticPr fontId="39"/></si><si><r><t>　　　　　　　　　　　　　　　　　　　説明者</t></r><r><rPr><u/><sz val="11"/><color theme="1"/><rFont val="ＭＳ ゴシック"/><family val="3"/><charset val="128"/></rPr><t>　　　髙野　哲　　　</t></r><r><rPr><sz val="11"/><color theme="1"/><rFont val="ＭＳ ゴシック"/><family val="3"/><charset val="128"/></rPr><t>印　　</t></r><rPh sb="25" eb="27"><t>タカノ</t></rPh><rPh sb="28" eb="29"><t>テツ</t></rPh><phoneticPr fontId="39"/></si><si><t>特殊寝台</t><rPh sb="0" eb="2"><t>トクシュ</t></rPh><rPh sb="2" eb="4"><t>シンダイ</t></rPh><phoneticPr fontId="39"/></si><si><t>特殊寝台付属品</t><rPh sb="0" eb="2"><t>トクシュ</t></rPh><rPh sb="2" eb="4"><t>シンダイ</t></rPh><rPh sb="4" eb="7"><t>フゾクヒン</t></rPh><phoneticPr fontId="39"/></si><si><t>　　　　＜管理者名＞　　　堂　面　　憲　史　　　  ㊞</t><rPh sb="13" eb="14"><t>ドウ</t></rPh><rPh sb="15" eb="16"><t>メン</t></rPh><rPh sb="18" eb="19"><t>ケン</t></rPh><rPh sb="20" eb="21"><t>シ</t></rPh><phoneticPr fontId="39"/></si><si><r><t>　　</t></r><r><rPr><u/><sz val="10"/><color theme="1"/><rFont val="ＭＳ ゴシック"/><family val="3"/><charset val="128"/></rPr><t>氏名　　堂面　憲史　　　電話番号　　０４３－２１４－１６７０</t></r><rPh sb="6" eb="7"><t>ドウ</t></rPh><rPh sb="7" eb="8"><t>メン</t></rPh><rPh sb="9" eb="10"><t>ケン</t></rPh><rPh sb="10" eb="11"><t>シ</t></rPh><phoneticPr fontId="39"/></si><si><t>　　　　　　＜管理者名＞　　　堂面　憲史　　印</t><rPh sb="15" eb="16"><t>ドウ</t></rPh><rPh sb="16" eb="17"><t>メン</t></rPh><rPh sb="18" eb="19"><t>ケン</t></rPh><rPh sb="19" eb="20"><t>シ</t></rPh><phoneticPr fontId="39"/></si><si><r><t>契約締結日　　　　</t></r><r><rPr><sz val="10"/><color rgb="FFFF0000"/><rFont val="ＭＳ Ｐゴシック"/><family val="3"/><charset val="128"/></rPr><t>令和　3　年　　月　　日</t></r><rPh sb="9" eb="11"><t>レイワ</t></rPh><phoneticPr fontId="39"/></si><si><t>令和　3　年　　月　　日</t><phoneticPr fontId="39"/></si><si><r><t>　１　この契約の契約期間は、</t></r><r><rPr><sz val="10"/><color rgb="FFFF0000"/><rFont val="ＭＳ Ｐゴシック"/><family val="3"/><charset val="128"/></rPr><t>令和　3　年　　月　　日</t></r><r><rPr><sz val="10"/><color theme="1"/><rFont val="ＭＳ Ｐゴシック"/><family val="3"/><charset val="128"/></rPr><t>から利用者の要介護認定又は要支援認定の有効期限満了</t></r><phoneticPr fontId="39"/></si><si><t>堂面　憲史　　　TEL　043-214-1670</t><rPh sb="0" eb="1"><t>ドウ</t></rPh><rPh sb="1" eb="2"><t>メン</t></rPh><rPh sb="3" eb="4"><t>ケン</t></rPh><rPh sb="4" eb="5"><t>シ</t></rPh><phoneticPr fontId="39"/></si><si><t>＜担　　　　当＞　　管理者　    　　堂面　憲史　　　　　　　　　＜電話＞  043-214-1670</t><rPh sb="20" eb="21"><t>ドウ</t></rPh><rPh sb="21" eb="22"><t>メン</t></rPh><rPh sb="23" eb="24"><t>ケン</t></rPh><rPh sb="24" eb="25"><t>シ</t></rPh><phoneticPr fontId="39"/></si><si><t>日</t><rPh sb="0" eb="1"><t>ニチ</t></rPh><phoneticPr fontId="39"/></si><si><t>月</t><rPh sb="0" eb="1"><t>ガツ</t></rPh><phoneticPr fontId="39"/></si><si><r><t>　　　　　　　　　　　　　　　　　　　説明者</t></r><r><rPr><u/><sz val="11"/><color theme="1"/><rFont val="ＭＳ ゴシック"/><family val="3"/><charset val="128"/></rPr><t>　　　鶴岡　隆幸　　　</t></r><r><rPr><sz val="11"/><color theme="1"/><rFont val="ＭＳ ゴシック"/><family val="3"/><charset val="128"/></rPr><t>印　　</t></r><rPh sb="25" eb="30"><t>ツルオカ</t></rPh><phoneticPr fontId="39"/></si><si><r><t>　　　　　　　　　　　　　　　　　　　説明者</t></r><r><rPr><u/><sz val="11"/><color theme="1"/><rFont val="ＭＳ ゴシック"/><family val="3"/><charset val="128"/></rPr><t>　　　澤田　拓馬　　　</t></r><r><rPr><sz val="11"/><color theme="1"/><rFont val="ＭＳ ゴシック"/><family val="3"/><charset val="128"/></rPr><t>印　　</t></r><rPh sb="25" eb="27"><t>サワダ</t></rPh><rPh sb="28" eb="29"><t>タク</t></rPh><rPh sb="29" eb="30"><t>ウマ</t></rPh><phoneticPr fontId="39"/></si><si><t>　　　　＜管理者名＞　　　松　倉　　賢　介　　　  ㊞</t><rPh sb="13" eb="14"><t>マツ</t></rPh><rPh sb="15" eb="16"><t>クラ</t></rPh><rPh sb="18" eb="19"><t>ケン</t></rPh><rPh sb="20" eb="21"><t>カイ</t></rPh><phoneticPr fontId="39"/></si><si><t>＜担　　　　当＞　　管理者　    　　松倉　賢介　　　　　　　　　＜電話＞  043-214-1670</t><rPh sb="20" eb="22"><t>マツクラ</t></rPh><rPh sb="23" eb="24"><t>ケン</t></rPh><rPh sb="24" eb="25"><t>スケ</t></rPh><phoneticPr fontId="39"/></si><si><t>　　　　　　＜管理者名＞　　　松倉　賢介　　印</t><rPh sb="15" eb="17"><t>マツクラ</t></rPh><rPh sb="18" eb="19"><t>ケン</t></rPh><rPh sb="19" eb="20"><t>スケ</t></rPh><phoneticPr fontId="39"/></si><si><r><t>　　</t></r><r><rPr><u/><sz val="10"/><color theme="1"/><rFont val="ＭＳ ゴシック"/><family val="3"/><charset val="128"/></rPr><t>氏名　　松倉　賢介　　　電話番号　　０４３－２１４－１６７０</t></r><rPh sb="6" eb="8"><t>マツクラ</t></rPh><rPh sb="9" eb="10"><t>ケン</t></rPh><rPh sb="10" eb="11"><t>スケ</t></rPh><phoneticPr fontId="39"/></si><si><t>松倉　賢介　　TEL　043-214-1670</t><rPh sb="0" eb="2"><t>マツクラ</t></rPh><rPh sb="3" eb="4"><t>ケン</t></rPh><rPh sb="4" eb="5"><t>スケ</t></rPh><phoneticPr fontId="39"/></si><si><t>松倉　賢介　　　TEL　043-214-1670</t><rPh sb="0" eb="2"><t>マツクラ</t></rPh><rPh sb="3" eb="4"><t>ケン</t></rPh><rPh sb="4" eb="5"><t>スケ</t></rPh><phoneticPr fontId="39"/></si><si><t>　　　　　　＜管理者名＞　　　松倉　賢介　印</t><rPh sb="15" eb="17"><t>マツクラ</t></rPh><rPh sb="18" eb="19"><t>ケン</t></rPh><rPh sb="19" eb="20"><t>スケ</t></rPh><phoneticPr fontId="39"/></si><si><r><t>契約締結日　　　　</t></r><r><rPr><sz val="10"/><color rgb="FFFF0000"/><rFont val="ＭＳ Ｐゴシック"/><family val="3"/><charset val="128"/></rPr><t>令和　　4　　年　　　　月　　　　　日</t></r><rPh sb="9" eb="11"><t>レイワ</t></rPh><phoneticPr fontId="39"/></si><si><r><t>　１　この契約の契約期間は、</t></r><r><rPr><sz val="10"/><color rgb="FFFF0000"/><rFont val="ＭＳ Ｐゴシック"/><family val="3"/><charset val="128"/></rPr><t>令和　4　年　　　　月　　　　日</t></r><r><rPr><sz val="10"/><color theme="1"/><rFont val="ＭＳ Ｐゴシック"/><family val="3"/><charset val="128"/></rPr><t>から利用者の要介護認定又は要支援認定の有効期限満了</t></r><phoneticPr fontId="39"/></si><si><t>令和　　4　　年　　　月　　　　日</t><phoneticPr fontId="39"/></si><si><t>　　　　＜管理者名＞　　　佐　藤　　勝　利　　　  ㊞</t><rPh sb="13" eb="14"><t>サ</t></rPh><rPh sb="15" eb="16"><t>フジ</t></rPh><rPh sb="18" eb="19"><t>カツ</t></rPh><rPh sb="20" eb="21"><t>リ</t></rPh><phoneticPr fontId="39"/></si><si><t>＜担　　　　当＞　　管理者　    　　佐藤　勝利　　　　　　　　　＜電話＞  043-214-1670</t><rPh sb="20" eb="22"><t>サトウ</t></rPh><rPh sb="23" eb="25"><t>ショウリ</t></rPh><phoneticPr fontId="39"/></si><si><t>電話番号　　０４３－２１４－１６７０</t></si><si><t>氏名　　</t><phoneticPr fontId="39"/></si><si><t>担当:</t><rPh sb="0" eb="2"><t>タントウ</t></rPh><phoneticPr fontId="39"/></si><si><t>管理者:</t><rPh sb="0" eb="3"><t>カンリシャ</t></rPh><phoneticPr fontId="39"/></si><si><t>月</t><rPh sb="0" eb="1"><t>ガツ</t></rPh><phoneticPr fontId="39"/></si><si><t>日</t><rPh sb="0" eb="1"><t>ニチ</t></rPh><phoneticPr fontId="39"/></si><si><t>年</t><rPh sb="0" eb="1"><t>ネン</t></rPh><phoneticPr fontId="39"/></si><si><t>　　　　　　　　　　　　　　　　　　　説明者</t><phoneticPr fontId="39"/></si><si><t>　　　　　　＜管理者名＞　</t><phoneticPr fontId="39"/></si><si><t>開始日：</t><rPh sb="0" eb="3"><t>カイシビ</t></rPh><phoneticPr fontId="39"/></si><si><t>　　　合が２割または３割の方はこれに２または３を乗じた金額が負担額となります。</t></si><si><t>　　　下記の「利用者負担額」は介護保険の負担割合が1割の方の場合の負担額となります。介護保険の負担割</t><rPh sb="3" eb="5"><t>カキ</t></rPh><rPh sb="7" eb="10"><t>リヨウシャ</t></rPh><rPh sb="10" eb="12"><t>フタン</t></rPh><rPh sb="12" eb="13"><t>ガク</t></rPh><rPh sb="15" eb="17"><t>カイゴ</t></rPh><rPh sb="17" eb="19"><t>ホケン</t></rPh><rPh sb="20" eb="22"><t>フタン</t></rPh><rPh sb="22" eb="24"><t>ワリアイ</t></rPh><rPh sb="26" eb="27"><t>ワリ</t></rPh><rPh sb="28" eb="29"><t>カタ</t></rPh><rPh sb="30" eb="32"><t>バアイ</t></rPh><rPh sb="33" eb="35"><t>フタン</t></rPh><rPh sb="35" eb="36"><t>ガク</t></rPh><rPh sb="42" eb="44"><t>カイゴ</t></rPh><rPh sb="44" eb="46"><t>ホケン</t></rPh><rPh sb="47" eb="49"><t>フタン</t></rPh><rPh sb="49" eb="50"><t>ワリ</t></rPh><phoneticPr fontId="38"/></si><si><t>2022.04.05</t><phoneticPr fontId="39"/></si><si><t>佐藤勝利</t><rPh sb="0" eb="2"><t>サトウ</t></rPh><rPh sb="2" eb="4"><t>カツトシ</t></rPh><phoneticPr fontId="39"/></si><si><t>初月価格</t><rPh sb="0" eb="2"><t>ショゲツ</t></rPh><rPh sb="2" eb="4"><t>カカク</t></rPh><phoneticPr fontId="39"/></si><si><t>種目</t><rPh sb="0" eb="2"><t>シュモク</t></rPh><phoneticPr fontId="39"/></si><si><t>福祉用具貸与商品</t></si><si><t>金額</t><rPh sb="0" eb="2"><t>キンガク</t></rPh><phoneticPr fontId="39"/></si><si><t>連動用</t><rPh sb="0" eb="3"><t>レンドウヨウ</t></rPh><phoneticPr fontId="39"/></si><si><t>数量</t><rPh sb="0" eb="2"><t>スウリョウ</t></rPh><phoneticPr fontId="39"/></si><si><t>通常</t><rPh sb="0" eb="2"><t>ツウジョウ</t></rPh><phoneticPr fontId="39"/></si><si><t>半額</t><rPh sb="0" eb="2"><t>ハンガク</t></rPh><phoneticPr fontId="39"/></si><si><t>澤田　拓馬</t><rPh sb="0" eb="5"><t>サワダ</t></rPh><phoneticPr fontId="39"/></si><si><t>契約締結日</t><phoneticPr fontId="39"/></si><si><t>令和</t><rPh sb="0" eb="2"><t>レイワ</t></rPh><phoneticPr fontId="39"/></si><si><t>年号：</t><rPh sb="0" eb="2"><t>ネンゴウ</t></rPh><phoneticPr fontId="39"/></si><si><t>第３項の規定に基づき、株式会社インフォゲート、フランスベッド株式会社、野口株式会社</t><rPh sb="0" eb="1"><t>ダイ</t></rPh><phoneticPr fontId="39"/></si><si><t>株式会社日本ケアサプライ、ケアレックス株式会社にこの業務を委託し、業務委託契約書を取り交わした上で</t><phoneticPr fontId="39"/></si><si><t>事業所は委託の契約の内容において、保管及び消毒が適切な方法により行われていることを担保します。</t><phoneticPr fontId="39"/></si><si><t>　　　　　サービスの終了を希望する日の1週間前までに文書又は口頭で通知することにより、サービスを終了することができ</t><phoneticPr fontId="39"/></si><si><t>たよレールBZ-N02 マット付</t></si><si><t>契約</t></si></sst>